{"cameraMode":{"drawMode":0,"name":"Shaded","section":"Shading Mode"},"sceneLighting":true,"audioPlay":false,"sceneViewState":{"m_AlwaysRefresh":false,"showFog":false,"showSkybox":true,"showFlares":true,"showImageEffects":true,"showParticleSystems":true,"showVisualEffectGraphs":true,"m_FxEnabled":true},"in2DMode":false,"pivot":{"x":585.3565673828125,"y":276.07989501953127,"z":38.4442138671875},"rotation":{"x":-0.0878685712814331,"y":-0.02268896996974945,"z":0.0015262289671227337,"w":-0.9966441988945007},"size":330.5290222167969,"orthographic":false}